nai_generate/__init__.py
nai_generate/app.py
nai_generate/cli.py
nai_generate/novelai_wrapper.py
nai_generate-0.1.0.dist-info/METADATA
nai_generate-0.1.0.dist-info/WHEEL
nai_generate-0.1.0.dist-info/entry_points.txt
nai_generate-0.1.0.dist-info/licenses/LICENSE
nai_generate-0.1.0.dist-info/RECORD
