Metadata-Version: 2.4
Name: nai-generate
Version: 0.1.0
Summary: Add your description here
Author-email: yada <trojblue@gmail.com>
License-File: LICENSE
Requires-Python: >=3.10
Requires-Dist: curl-cffi>=0.9.0
Requires-Dist: dynamicprompts>=0.31.0
Requires-Dist: gradio>=5.20.0
Requires-Dist: pillow>=11.1.0
Requires-Dist: requests>=2.32.3
Requires-Dist: toml>=0.10.2
